spyks/__init__.py
spyks/_version.py
spyks/analyze.py
spyks/build.py
spyks/codegen.py
spyks/core.py
spyks/ipopt.py
spyks/tools.py
spyks/validate.py
spyks/templates/head.cpp
spyks/templates/model_continuous.cpp
spyks/templates/model_reset.cpp
spyks-0.7.0.dist-info/METADATA
spyks-0.7.0.dist-info/WHEEL
spyks-0.7.0.dist-info/entry_points.txt
spyks-0.7.0.dist-info/top_level.txt
spyks-0.7.0.dist-info/RECORD
