Metadata-Version: 2.1
Name: spyks
Version: 0.7.0
Summary: Generate fast c++ code to integrate dynamical neuron models
Home-page: https://github.com/melizalab/neurobank
Author: Dan Meliza
Author-email: dan@meliza.org
Maintainer: Dan Meliza
Maintainer-email: dan@meliza.org
License: GNU General Public License (GPL)
Classifier: Development Status :: 3 - Alpha
Classifier: Intended Audience :: Science/Research
Classifier: License :: OSI Approved :: GNU General Public License (GPL)
Classifier: Programming Language :: Python
Classifier: Topic :: Scientific/Engineering
Classifier: Operating System :: Unix
Classifier: Operating System :: POSIX :: Linux
Classifier: Operating System :: MacOS :: MacOS X
Classifier: Natural Language :: English
Requires-Python: >=3.5
Requires-Dist: pybind11 (>=2.2.0)
Requires-Dist: Pint (>=0.7)
Requires-Dist: ruamel.yaml (>=0.13)
Requires-Dist: sympy (>=1.0)
Requires-Dist: numpy (>=1.22)
